jbussdieker/storage/__init__.py
jbussdieker/storage/cli.py
jbussdieker/storage/store.py
jbussdieker_storage-0.2.1.dist-info/licenses/LICENSE
jbussdieker_storage-0.2.1.dist-info/METADATA
jbussdieker_storage-0.2.1.dist-info/WHEEL
jbussdieker_storage-0.2.1.dist-info/entry_points.txt
jbussdieker_storage-0.2.1.dist-info/top_level.txt
jbussdieker_storage-0.2.1.dist-info/RECORD
