Metadata-Version: 2.4
Name: jbussdieker-storage
Version: 0.2.1
Summary: A modern Python development toolkit.
Author-email: "Joshua B. Bussdieker" <jbussdieker@gmail.com>
Maintainer-email: "Joshua B. Bussdieker" <jbussdieker@gmail.com>
License-Expression: MIT
Project-URL: Homepage, https://github.com/jbussdieker/jbussdieker-storage
Project-URL: Documentation, https://github.com/jbussdieker/jbussdieker-storage/blob/main/README.md
Project-URL: Repository, https://github.com/jbussdieker/jbussdieker-storage
Project-URL: Issues, https://github.com/jbussdieker/jbussdieker-storage/issues
Project-URL: Changelog, https://github.com/jbussdieker/jbussdieker-storage/blob/main/CHANGELOG.md
Classifier: Topic :: Software Development :: Build Tools
Classifier: Development Status :: 3 - Alpha
Classifier: Programming Language :: Python :: 3
Classifier: Programming Language :: Python :: 3.9
Classifier: Programming Language :: Python :: 3.10
Classifier: Programming Language :: Python :: 3.11
Classifier: Programming Language :: Python :: 3.12
Classifier: Programming Language :: Python :: 3.13
Classifier: Operating System :: OS Independent
Classifier: Environment :: Console
Classifier: Intended Audience :: Developers
Classifier: Natural Language :: English
Classifier: Typing :: Typed
Requires-Python: >=3.9
License-File: LICENSE
Requires-Dist: boto3
Dynamic: license-file
